Workbook

Sheet 總覽
A1: 台灣 AI／半導體供應鏈 AOI／光學檢測／量測設備商總整表
A3: 更新基準 | B3: 2026-03-12（台北時間） | D3: 使用說明 | E3: 1) 先看「投資排序」鎖定核心；2) 再看各分類 sheet；3) 每家公司另有法人備忘錄 sheet。
A4: 整理範圍 | B4: 台灣公開市場（上市／上櫃／興櫃）中，已明確切入 AI、半導體前段、先進封裝、IC 載板、AI 伺服器 PCB AOI，及矽光子/CPO 光學耦合與檢測設備之公司。
A5: 公司數 | B5: 12
A6: 分類數 | B6: 5
A7: 核心觀察 | B7: 由田、牧德、德律、倍利科、晶彩科、竑騰為核心；大量、均豪、高明鐵為交叉設備中較有彈性者。
A10: 分類 | B10: 家數
A11: 半導體前段 | B11: 7
A12: 先進封裝 | B12: 10
A13: IC載板 | B13: 5
A14: AI伺服器PCB AOI | B14: 5
A15: 矽光子/CPO 光學耦合與檢測 | B15: 1

Sheet 公司總表
A1: 市場別 | B1: 代號 | C1: 公司 | D1: 主分類 | E1: 次分類 | F1: 分類標籤 | G1: 上游供應商 | H1: 確定客戶/客群 | I1: 產品站點 | J1: 2026成長催化 | K1: 最大風險 | L1: 買點邏輯 | M1: 停損邏輯 | N1: 最後結論 | O1: 來源1 | P1: 來源2
A2: 上櫃 | B2: 3455 | C2: 由田 | D2: 核心AOI | E2: 半導體前段 / 先進封裝 / IC載板 / AI伺服器PCB AOI | F2: 半導體前段、先進封裝、IC載板、AI伺服器PCB AOI | G2: 工業相機、鏡頭、光源、精密平台、機器視覺與演算法模組供應鏈 | H2: 前十大OSAT過半、兩岸領先封裝廠、東南亞封裝客戶；公司並規劃2026年打入3家晶圓廠 | I2: Bare wafer AOI、黃光/RDL AOI、Fan-out/Interposer AOI、IC載板AOI、AI server主板AOI、高階OM | J2: 半導體營收有望倍增；營收認列高峰落在2026年Q2後；由封裝跨入前段晶圓廠，產品涵蓋Wafer/FOPLP/Unit形式 | K2: 驗證與認列節奏不平滑、交期較長；若晶圓廠導入遞延，市場會先修正估值 | L2: 不追長紅；等量縮回測10/20日線不破、MACD未翻空、KD回落後再上彎時分批承接 | M2: 跌破前波平台且爆量失守20日線先砍半；若連60日線都失守，代表認列預期轉弱應退場 | N2: 最像『半導體AOI平台股』，產品站點最完整，適合作為AOI主倉核心 | O2: https://www.ftnn.com.tw/news/512660 | P2: https://news.cnyes.com/news/id/5633834
A3: 上市 | B3: 3563 | C3: 牧德 | D3: 核心AOI | E3: 先進封裝 / 半導體前段 / IC載板 / AI伺服器PCB AOI | F3: 半導體前段、先進封裝、IC載板、AI伺服器PCB AOI | G3: 光學、控制、量測與演算法模組供應鏈 | H3: 日月光為公開驗證客戶與股東；另以全球PCB與高階載板客群為主 | I3: PCB AOI、Packaged IC Inspection & Metrology、Wafer AOI、FOWLP/FOPLP/矽光子檢查設備 | J3: AI伺服器/HPC/高階IC載板需求延續；半導體檢測設備持續推進客戶導入；2025 EPS 15.8元、2026前2月營收年增7.81% | K3: 估值已高、好消息已部分反映；若Wafer/FOPLP驗證放量時程遞延，股價容易高檔震盪 | L3: 只做強勢股拉回買；等5日線乖離收斂、量縮回測10日線或前高不破再接 | M3: 爆量長黑跌破20日線先降部位；跌破前波平台且MACD柱狀體翻負擴大則不戀戰 | N3: 品質最好、客戶最硬的AOI股之一，但不再是便宜貨，適合拉回承接 | O3: https://news.cnyes.com/news/id/6360450 | P3: https://www.cna.com.tw/news/aie/202506190204.aspx
A4: 上市 | B4: 3535 | C4: 晶彩科 | D4: 核心AOI | E4: 先進封裝 / 半導體前段 / IC載板 | F4: 半導體前段、先進封裝、IC載板 | G4: 光學檢測、量測平台、AI缺陷辨識與對位模組供應鏈 | H4: 知名封測大廠採用；半導體設備已通過認證並取得訂單（公開未點名） | I4: Wafer AI AOI、3D IC Die Location、FOPLP/FOWLP Die Location Metrology、TGV/玻璃基板檢量測 | J4: FOPLP/TGV/玻璃基板與AI AOI需求升溫；2026年訂單看倍數成長，第四季以來營收明顯回升 | K4: 客製案與量產案比重高，財報波動大；若FOPLP/TGV量產時程不如預期，題材先回檔 | L4: 不追連續漲停；等爆量後首次量縮整理，確認10日線與缺口有守再介入 | M4: 失守平台且量能擴大時應快速停損，避免題材退潮 | N4: 真正的價值在AOI+Metrology，若FOPLP/TGV成形，彈性很大 | O4: https://www.chinatimes.com/newspapers/20260122000409-260206 | P4: https://www.favite.com/en/
A5: 上市 | B5: 3030 | C5: 德律 | D5: 核心AOI | E5: 先進封裝 / AI伺服器PCB AOI | F5: 先進封裝、AI伺服器PCB AOI | G5: 感測、光學、X-ray、運控與測試模組供應鏈 | H5: 網通/伺服器為最大應用領域，並切入晶圓廠與OSAT供應鏈（公開未逐一點名） | I5: SPI、AOI、AXI、ICT/BT/MDA、AI-powered 3D SEMI AOI，延伸至WLP/TSV/TGV/Glass RDL | J5: AI基建、AI伺服器與先進封裝帶動；2025年營收84.67億元創高，2026年前2月持續雙位數成長 | K5: 股價不便宜但彈性通常不如題材股；若伺服器CAPEX轉弱，評價易受壓抑 | L5: 趨勢回檔承接；量縮回測10/20日線不破可分批 | M5: 高檔爆量長黑、跌破20日線且5日線下彎時收縮部位 | N5: 最穩健的AOI/檢測配置之一，適合保守型資金 | O5: https://www.ftnn.com.tw/news/512878 | P5: https://www.ftnn.com.tw/news/449172
A6: 上市 | B6: 6658 | C6: 聯策 | D6: 交叉設備 | E6: AI伺服器PCB AOI / IC載板 / 半導體前段 | F6: 半導體前段、IC載板、AI伺服器PCB AOI | G6: AI機器視覺、高階自動化、智慧製程整合供應鏈 | H6: 一線PCB/載板客戶、泰國載板客戶；重要股東含迅得、臻鼎-KY；半導體客戶未公開點名 | I6: AI機器視覺設備、檢測設備產線、PCB/載板自動化，並跨入晶圓檢測/量測設備 | J6: 新生廠量能開出、東南亞PCB外移擴產、半導體設備研發導入；2025 EPS 1.38元，訂單能見度到2026年Q2 | K6: 半導體設備營收占比尚未顯性化；若只是PCB自動化成長，市場不會給純AOI估值 | L6: 站穩20日線、量能溫和放大、回測不破再買，適合作補漲與轉骨觀察股 | M6: 跌回整理平台下緣或放量跌破20日線就先退 | N6: 值得納入，但屬第二圈觀察，不應與由田/牧德/德律混為同級 | O6: https://uanalyze.com.tw/articles/7030747426 | P6: https://udn.com/news/story/7253/8795635
A7: 上櫃 | B7: 6877 | C7: 鏵友益 | D7: 核心AOI | E7: 先進封裝 / 半導體前段 | F7: 半導體前段、先進封裝 | G7: AOI模組、自動化零組件與OEM配套供應鏈 | H7: 日月光供應鏈、半導體封測與晶圓客群；與牧德結盟（部分客戶公開報導曾提及聯電/日月光） | I7: AOI檢測設備、智能自動化設備、半導體微觀/鉅觀視覺檢查、Wafer AOI | J7: 轉型半導體視覺檢查業務，與牧德結盟可望擴大Wafer AOI與封裝自動化接單 | K7: 2025 EPS僅0.59元，轉型尚未完全反映；獲利波動大 | L7: 只能用轉機股打法；等營收連續回升、量價同步、站穩季線再看 | M7: 跌破季線且無量承接時先退出 | N7: 小而純但仍在轉骨，不適合當主倉 | O7: https://www.chinatimes.com/newspapers/20250319000332-260206 | P7: https://gfemobile.cnyes.com/news/id/6342921
A8: 上櫃 | B8: 7751 | C8: 竑騰 | D8: 核心AOI | E8: 先進封裝 AOI / AI散熱封裝 | F8: 先進封裝 | G8: 精密機構、點膠/壓合、熱壓控制、AOI視覺與TIM製程模組 | H8: 台積電、日月光、矽品、力成等前七大封測業者供應鏈 | I8: 點膠植片壓合機、Metal TIM/散熱片貼合、自動光學檢測（AOI）設備 | J8: AI/GPU/HPC高功耗帶動散熱封裝升級；2026年1月營收年增80.57%，市場看好接單延續 | K8: 高成長也高波動；客戶集中於封測龍頭，若CAPEX遞延彈性會反向放大 | L8: 等第一次大漲後量縮整理、5日線重新上彎再介入，採分批策略 | M8: 失守20日線且帶量先退；高檔爆量長黑吞噬前兩日視為主力換手失敗 | N8: AI散熱/先進封裝黑馬，硬邏輯成立，但波動極大 | O8: https://money.udn.com/money/amp/story/5607/9341183 | P8: https://www.taisounds.com/news/content/76/204366
A9: 興櫃/即將上市 | B9: 7822 | C9: 倍利科 | D9: 核心AOI | E9: 半導體前段 / 先進封裝 | F9: 半導體前段、先進封裝 | G9: 光學、精密機械、電控、軟體與AI整合供應鏈 | H9: 晶圓製造廠、先進封裝廠、記憶體廠；已導入逾10家半導體客戶、上線逾800台 | I9: 高階Auto OM、高倍率量測（CD/OVL）、AI ADC影像數據分析、缺陷辨識系統 | J9: 2025營收20.75億元年增187.82%；受惠先進製程/先進封裝擴產，2026預計3/30掛牌上市 | K9: 上市初期估值與流動性波動大；高成長基期下任何季節性放緩都會被放大 | L9: 不要追上市蜜月；等第一波情緒高點過後、回測關鍵均線有守再接 | M9: 跌破上市後第一個整理平台時嚴格停損 | N9: 最像AI原生AOI，技術護城河在AI缺陷資料庫與演算法 | O9: https://udn.com/news/story/7254/9359635 | P9: https://www.mnews.tw/external/mirrordaily49130
A10: 上櫃 | B10: 5443 | C10: 均豪 | D10: 交叉設備 | E10: 先進封裝 / IC載板 | F10: 先進封裝、IC載板 | G10: 檢、量、磨、拋與製程整合設備供應鏈 | H10: 封測大廠與再生晶圓客戶（公開未點名） | I10: CMP結合AOI檢測、多段拋光、白光檢測量測Bump高度/間距、IC載板AOI相關設備 | J10: AI晶片散熱與先進封裝升級；2026年半導體營收占比目標逾8成，再生晶圓與先進封測為雙主軸 | K10: 設備組合多元，市場難以給純AOI估值；若先進封裝CAPEX不如預期，題材張力會下降 | L10: 偏波段股打法；站穩20日線、量能溫和放大可續抱 | M10: 衝高後量價背離、跌回整理區時先減碼 | N10: 不是最純，但往往比市場想像中更受惠於先進封測設備整合 | O10: https://udn.com/news/story/7254/9367100 | P10: https://udn.com/news/story/7253/9132993
A11: 上市 | B11: 3167 | C11: 大量 | D11: 交叉設備 | E11: 先進封裝 / 半導體前段 / AI伺服器PCB AOI | F11: 半導體前段、先進封裝、AI伺服器PCB AOI | G11: 量測模組、AOI光學、自動化與機構供應鏈 | H11: 台積電、日月光等指標客戶 | I11: Wafer邊緣量測、CMP Pad量測、Step-height量測、FOPLP翹曲量測、AOI、自動化；對應SoIC/InFO/CoWoS | J11: 先進封裝相關量測與AOI設備出貨擴大；2025年部分訂單遞延至2026年，能見度延續 | K11: 股價曾快速飆漲，若單月營收或新單節奏不連續，修正會很快 | L11: 只在強勢整理後再發動時介入，不追噴出 | M11: 跌破月線且量增、KD/MACD同步走弱時停利/停損都要快 | N11: 關鍵不是有沒有AOI，而是已吃到台積電/日月光先進封裝量測站點 | O11: https://ec.ltn.com.tw/article/paper/1668066 | P11: https://news.cnyes.com/news/print/6262663
A12: 上櫃 | B12: 8064 | C12: 東捷 | D12: 交叉設備 | E12: 先進封裝 / 玻璃載板 / FOPLP | F12: 先進封裝 | G12: 雷射、光學量測與先進封裝製程設備模組供應鏈 | H12: 先進封裝與面板/FOPLP客戶（公開未逐一點名） | I12: RDL雷射線路修補設備（搭載自動光學量測）、玻璃載板雷射切割、AOI設備、電漿清潔 | J12: 先進封裝設備訂單增長，2026年半導體設備比重有望拉升到30%以上；受惠FOPLP與玻璃基板 | K12: 不是純AOI且營收認列偏集中；當主線轉向更純的AOI/封測設備股時容易被邊緣化 | L12: 題材輪動時短打；站穩季線再看 | M12: 跌破季線就撤，不當長抱核心 | N12: 能看，但排序應放後面，較適合次核心觀察 | O12: https://www.chinatimes.com/newspapers/20251127000364-260206 | P12: https://udn.com/news/story/7240/8581331
A13: 興櫃 | B13: 4573 | C13: 高明鐵 | D13: 交叉設備 | E13: 矽光子 / CPO 光學耦合與晶圓級測試 | F13: 矽光子/CPO 光學耦合與檢測 | G13: 六軸平台、AI影像伺服、6D雷射量測與高精度運動控制供應鏈 | H13: CPO光引擎、AI伺服器光模組與矽光晶圓測試/封裝客群；市場點名卡位台積電CPO鏈 | I13: 主動對準、晶圓級耦光測試、光引擎找光/對準/鎖光、CPO/矽光子封裝測試 | J13: 800G放量、1.6T少量生產與2026矽光子商轉；元月營收年增93.49%，受惠高速互連升級 | K13: 非傳統AOI主線；若CPO量產時程遞延，題材修正會很快，營收波動也較大 | L13: 放量突破平台後，等第一次量縮回測10/20日線不破再進 | M13: 跌回突破平台下方，或爆量長黑失守20日線先退 | N13: 應納入名單，但要獨立歸類為矽光子/CPO光學耦合與量測設備，不宜硬塞進傳統AOI核心 | O13: https://money.udn.com/money/story/5735/8985170 | P13: https://www.ftnn.com.tw/news/519647

Sheet Category_前段
A1: 半導體前段 廠商列表
A3: 市場別 | B3: 代號 | C3: 公司 | D3: 主分類 | E3: 次分類 | F3: 確定客戶/客群 | G3: 產品站點 | H3: 2026成長催化 | I3: 最後結論 | J3: 來源
A4: 上櫃 | B4: 3455 | C4: 由田 | D4: 核心AOI | E4: 半導體前段 / 先進封裝 / IC載板 / AI伺服器PCB AOI | F4: 前十大OSAT過半、兩岸領先封裝廠、東南亞封裝客戶；公司並規劃2026年打入3家晶圓廠 | G4: Bare wafer AOI、黃光/RDL AOI、Fan-out/Interposer AOI、IC載板AOI、AI server主板AOI、高階OM | H4: 半導體營收有望倍增；營收認列高峰落在2026年Q2後；由封裝跨入前段晶圓廠，產品涵蓋Wafer/FOPLP/Unit形式 | I4: 最像『半導體AOI平台股』，產品站點最完整，適合作為AOI主倉核心 | J4: https://www.ftnn.com.tw/news/512660
A5: 上市 | B5: 3563 | C5: 牧德 | D5: 核心AOI | E5: 先進封裝 / 半導體前段 / IC載板 / AI伺服器PCB AOI | F5: 日月光為公開驗證客戶與股東；另以全球PCB與高階載板客群為主 | G5: PCB AOI、Packaged IC Inspection & Metrology、Wafer AOI、FOWLP/FOPLP/矽光子檢查設備 | H5: AI伺服器/HPC/高階IC載板需求延續；半導體檢測設備持續推進客戶導入；2025 EPS 15.8元、2026前2月營收年增7.81% | I5: 品質最好、客戶最硬的AOI股之一，但不再是便宜貨，適合拉回承接 | J5: https://news.cnyes.com/news/id/6360450
A6: 上市 | B6: 3535 | C6: 晶彩科 | D6: 核心AOI | E6: 先進封裝 / 半導體前段 / IC載板 | F6: 知名封測大廠採用；半導體設備已通過認證並取得訂單（公開未點名） | G6: Wafer AI AOI、3D IC Die Location、FOPLP/FOWLP Die Location Metrology、TGV/玻璃基板檢量測 | H6: FOPLP/TGV/玻璃基板與AI AOI需求升溫；2026年訂單看倍數成長，第四季以來營收明顯回升 | I6: 真正的價值在AOI+Metrology，若FOPLP/TGV成形，彈性很大 | J6: https://www.chinatimes.com/newspapers/20260122000409-260206
A7: 上市 | B7: 6658 | C7: 聯策 | D7: 交叉設備 | E7: AI伺服器PCB AOI / IC載板 / 半導體前段 | F7: 一線PCB/載板客戶、泰國載板客戶；重要股東含迅得、臻鼎-KY；半導體客戶未公開點名 | G7: AI機器視覺設備、檢測設備產線、PCB/載板自動化，並跨入晶圓檢測/量測設備 | H7: 新生廠量能開出、東南亞PCB外移擴產、半導體設備研發導入；2025 EPS 1.38元，訂單能見度到2026年Q2 | I7: 值得納入，但屬第二圈觀察，不應與由田/牧德/德律混為同級 | J7: https://uanalyze.com.tw/articles/7030747426
A8: 上櫃 | B8: 6877 | C8: 鏵友益 | D8: 核心AOI | E8: 先進封裝 / 半導體前段 | F8: 日月光供應鏈、半導體封測與晶圓客群；與牧德結盟（部分客戶公開報導曾提及聯電/日月光） | G8: AOI檢測設備、智能自動化設備、半導體微觀/鉅觀視覺檢查、Wafer AOI | H8: 轉型半導體視覺檢查業務，與牧德結盟可望擴大Wafer AOI與封裝自動化接單 | I8: 小而純但仍在轉骨，不適合當主倉 | J8: https://www.chinatimes.com/newspapers/20250319000332-260206
A9: 興櫃/即將上市 | B9: 7822 | C9: 倍利科 | D9: 核心AOI | E9: 半導體前段 / 先進封裝 | F9: 晶圓製造廠、先進封裝廠、記憶體廠；已導入逾10家半導體客戶、上線逾800台 | G9: 高階Auto OM、高倍率量測（CD/OVL）、AI ADC影像數據分析、缺陷辨識系統 | H9: 2025營收20.75億元年增187.82%；受惠先進製程/先進封裝擴產，2026預計3/30掛牌上市 | I9: 最像AI原生AOI，技術護城河在AI缺陷資料庫與演算法 | J9: https://udn.com/news/story/7254/9359635
A10: 上市 | B10: 3167 | C10: 大量 | D10: 交叉設備 | E10: 先進封裝 / 半導體前段 / AI伺服器PCB AOI | F10: 台積電、日月光等指標客戶 | G10: Wafer邊緣量測、CMP Pad量測、Step-height量測、FOPLP翹曲量測、AOI、自動化；對應SoIC/InFO/CoWoS | H10: 先進封裝相關量測與AOI設備出貨擴大；2025年部分訂單遞延至2026年，能見度延續 | I10: 關鍵不是有沒有AOI，而是已吃到台積電/日月光先進封裝量測站點 | J10: https://ec.ltn.com.tw/article/paper/1668066

Sheet Category_先進封裝
A1: 先進封裝 廠商列表
A3: 市場別 | B3: 代號 | C3: 公司 | D3: 主分類 | E3: 次分類 | F3: 確定客戶/客群 | G3: 產品站點 | H3: 2026成長催化 | I3: 最後結論 | J3: 來源
A4: 上櫃 | B4: 3455 | C4: 由田 | D4: 核心AOI | E4: 半導體前段 / 先進封裝 / IC載板 / AI伺服器PCB AOI | F4: 前十大OSAT過半、兩岸領先封裝廠、東南亞封裝客戶；公司並規劃2026年打入3家晶圓廠 | G4: Bare wafer AOI、黃光/RDL AOI、Fan-out/Interposer AOI、IC載板AOI、AI server主板AOI、高階OM | H4: 半導體營收有望倍增；營收認列高峰落在2026年Q2後；由封裝跨入前段晶圓廠，產品涵蓋Wafer/FOPLP/Unit形式 | I4: 最像『半導體AOI平台股』，產品站點最完整，適合作為AOI主倉核心 | J4: https://www.ftnn.com.tw/news/512660
A5: 上市 | B5: 3563 | C5: 牧德 | D5: 核心AOI | E5: 先進封裝 / 半導體前段 / IC載板 / AI伺服器PCB AOI | F5: 日月光為公開驗證客戶與股東；另以全球PCB與高階載板客群為主 | G5: PCB AOI、Packaged IC Inspection & Metrology、Wafer AOI、FOWLP/FOPLP/矽光子檢查設備 | H5: AI伺服器/HPC/高階IC載板需求延續；半導體檢測設備持續推進客戶導入；2025 EPS 15.8元、2026前2月營收年增7.81% | I5: 品質最好、客戶最硬的AOI股之一，但不再是便宜貨，適合拉回承接 | J5: https://news.cnyes.com/news/id/6360450
A6: 上市 | B6: 3535 | C6: 晶彩科 | D6: 核心AOI | E6: 先進封裝 / 半導體前段 / IC載板 | F6: 知名封測大廠採用；半導體設備已通過認證並取得訂單（公開未點名） | G6: Wafer AI AOI、3D IC Die Location、FOPLP/FOWLP Die Location Metrology、TGV/玻璃基板檢量測 | H6: FOPLP/TGV/玻璃基板與AI AOI需求升溫；2026年訂單看倍數成長，第四季以來營收明顯回升 | I6: 真正的價值在AOI+Metrology，若FOPLP/TGV成形，彈性很大 | J6: https://www.chinatimes.com/newspapers/20260122000409-260206
A7: 上市 | B7: 3030 | C7: 德律 | D7: 核心AOI | E7: 先進封裝 / AI伺服器PCB AOI | F7: 網通/伺服器為最大應用領域，並切入晶圓廠與OSAT供應鏈（公開未逐一點名） | G7: SPI、AOI、AXI、ICT/BT/MDA、AI-powered 3D SEMI AOI，延伸至WLP/TSV/TGV/Glass RDL | H7: AI基建、AI伺服器與先進封裝帶動；2025年營收84.67億元創高，2026年前2月持續雙位數成長 | I7: 最穩健的AOI/檢測配置之一，適合保守型資金 | J7: https://www.ftnn.com.tw/news/512878
A8: 上櫃 | B8: 6877 | C8: 鏵友益 | D8: 核心AOI | E8: 先進封裝 / 半導體前段 | F8: 日月光供應鏈、半導體封測與晶圓客群；與牧德結盟（部分客戶公開報導曾提及聯電/日月光） | G8: AOI檢測設備、智能自動化設備、半導體微觀/鉅觀視覺檢查、Wafer AOI | H8: 轉型半導體視覺檢查業務，與牧德結盟可望擴大Wafer AOI與封裝自動化接單 | I8: 小而純但仍在轉骨，不適合當主倉 | J8: https://www.chinatimes.com/newspapers/20250319000332-260206
A9: 上櫃 | B9: 7751 | C9: 竑騰 | D9: 核心AOI | E9: 先進封裝 AOI / AI散熱封裝 | F9: 台積電、日月光、矽品、力成等前七大封測業者供應鏈 | G9: 點膠植片壓合機、Metal TIM/散熱片貼合、自動光學檢測（AOI）設備 | H9: AI/GPU/HPC高功耗帶動散熱封裝升級；2026年1月營收年增80.57%，市場看好接單延續 | I9: AI散熱/先進封裝黑馬，硬邏輯成立，但波動極大 | J9: https://money.udn.com/money/amp/story/5607/9341183
A10: 興櫃/即將上市 | B10: 7822 | C10: 倍利科 | D10: 核心AOI | E10: 半導體前段 / 先進封裝 | F10: 晶圓製造廠、先進封裝廠、記憶體廠；已導入逾10家半導體客戶、上線逾800台 | G10: 高階Auto OM、高倍率量測（CD/OVL）、AI ADC影像數據分析、缺陷辨識系統 | H10: 2025營收20.75億元年增187.82%；受惠先進製程/先進封裝擴產，2026預計3/30掛牌上市 | I10: 最像AI原生AOI，技術護城河在AI缺陷資料庫與演算法 | J10: https://udn.com/news/story/7254/9359635
A11: 上櫃 | B11: 5443 | C11: 均豪 | D11: 交叉設備 | E11: 先進封裝 / IC載板 | F11: 封測大廠與再生晶圓客戶（公開未點名） | G11: CMP結合AOI檢測、多段拋光、白光檢測量測Bump高度/間距、IC載板AOI相關設備 | H11: AI晶片散熱與先進封裝升級；2026年半導體營收占比目標逾8成，再生晶圓與先進封測為雙主軸 | I11: 不是最純，但往往比市場想像中更受惠於先進封測設備整合 | J11: https://udn.com/news/story/7254/9367100
A12: 上市 | B12: 3167 | C12: 大量 | D12: 交叉設備 | E12: 先進封裝 / 半導體前段 / AI伺服器PCB AOI | F12: 台積電、日月光等指標客戶 | G12: Wafer邊緣量測、CMP Pad量測、Step-height量測、FOPLP翹曲量測、AOI、自動化；對應SoIC/InFO/CoWoS | H12: 先進封裝相關量測與AOI設備出貨擴大；2025年部分訂單遞延至2026年，能見度延續 | I12: 關鍵不是有沒有AOI，而是已吃到台積電/日月光先進封裝量測站點 | J12: https://ec.ltn.com.tw/article/paper/1668066
A13: 上櫃 | B13: 8064 | C13: 東捷 | D13: 交叉設備 | E13: 先進封裝 / 玻璃載板 / FOPLP | F13: 先進封裝與面板/FOPLP客戶（公開未逐一點名） | G13: RDL雷射線路修補設備（搭載自動光學量測）、玻璃載板雷射切割、AOI設備、電漿清潔 | H13: 先進封裝設備訂單增長，2026年半導體設備比重有望拉升到30%以上；受惠FOPLP與玻璃基板 | I13: 能看，但排序應放後面，較適合次核心觀察 | J13: https://www.chinatimes.com/newspapers/20251127000364-260206

Sheet Category_IC載板
A1: IC載板 廠商列表
A3: 市場別 | B3: 代號 | C3: 公司 | D3: 主分類 | E3: 次分類 | F3: 確定客戶/客群 | G3: 產品站點 | H3: 2026成長催化 | I3: 最後結論 | J3: 來源
A4: 上櫃 | B4: 3455 | C4: 由田 | D4: 核心AOI | E4: 半導體前段 / 先進封裝 / IC載板 / AI伺服器PCB AOI | F4: 前十大OSAT過半、兩岸領先封裝廠、東南亞封裝客戶；公司並規劃2026年打入3家晶圓廠 | G4: Bare wafer AOI、黃光/RDL AOI、Fan-out/Interposer AOI、IC載板AOI、AI server主板AOI、高階OM | H4: 半導體營收有望倍增；營收認列高峰落在2026年Q2後；由封裝跨入前段晶圓廠，產品涵蓋Wafer/FOPLP/Unit形式 | I4: 最像『半導體AOI平台股』，產品站點最完整，適合作為AOI主倉核心 | J4: https://www.ftnn.com.tw/news/512660
A5: 上市 | B5: 3563 | C5: 牧德 | D5: 核心AOI | E5: 先進封裝 / 半導體前段 / IC載板 / AI伺服器PCB AOI | F5: 日月光為公開驗證客戶與股東；另以全球PCB與高階載板客群為主 | G5: PCB AOI、Packaged IC Inspection & Metrology、Wafer AOI、FOWLP/FOPLP/矽光子檢查設備 | H5: AI伺服器/HPC/高階IC載板需求延續；半導體檢測設備持續推進客戶導入；2025 EPS 15.8元、2026前2月營收年增7.81% | I5: 品質最好、客戶最硬的AOI股之一，但不再是便宜貨，適合拉回承接 | J5: https://news.cnyes.com/news/id/6360450
A6: 上市 | B6: 3535 | C6: 晶彩科 | D6: 核心AOI | E6: 先進封裝 / 半導體前段 / IC載板 | F6: 知名封測大廠採用；半導體設備已通過認證並取得訂單（公開未點名） | G6: Wafer AI AOI、3D IC Die Location、FOPLP/FOWLP Die Location Metrology、TGV/玻璃基板檢量測 | H6: FOPLP/TGV/玻璃基板與AI AOI需求升溫；2026年訂單看倍數成長，第四季以來營收明顯回升 | I6: 真正的價值在AOI+Metrology，若FOPLP/TGV成形，彈性很大 | J6: https://www.chinatimes.com/newspapers/20260122000409-260206
A7: 上市 | B7: 6658 | C7: 聯策 | D7: 交叉設備 | E7: AI伺服器PCB AOI / IC載板 / 半導體前段 | F7: 一線PCB/載板客戶、泰國載板客戶；重要股東含迅得、臻鼎-KY；半導體客戶未公開點名 | G7: AI機器視覺設備、檢測設備產線、PCB/載板自動化，並跨入晶圓檢測/量測設備 | H7: 新生廠量能開出、東南亞PCB外移擴產、半導體設備研發導入；2025 EPS 1.38元，訂單能見度到2026年Q2 | I7: 值得納入，但屬第二圈觀察，不應與由田/牧德/德律混為同級 | J7: https://uanalyze.com.tw/articles/7030747426
A8: 上櫃 | B8: 5443 | C8: 均豪 | D8: 交叉設備 | E8: 先進封裝 / IC載板 | F8: 封測大廠與再生晶圓客戶（公開未點名） | G8: CMP結合AOI檢測、多段拋光、白光檢測量測Bump高度/間距、IC載板AOI相關設備 | H8: AI晶片散熱與先進封裝升級；2026年半導體營收占比目標逾8成，再生晶圓與先進封測為雙主軸 | I8: 不是最純，但往往比市場想像中更受惠於先進封測設備整合 | J8: https://udn.com/news/story/7254/9367100

Sheet Category_AI伺服器PCB
A1: AI伺服器PCB AOI 廠商列表
A3: 市場別 | B3: 代號 | C3: 公司 | D3: 主分類 | E3: 次分類 | F3: 確定客戶/客群 | G3: 產品站點 | H3: 2026成長催化 | I3: 最後結論 | J3: 來源
A4: 上櫃 | B4: 3455 | C4: 由田 | D4: 核心AOI | E4: 半導體前段 / 先進封裝 / IC載板 / AI伺服器PCB AOI | F4: 前十大OSAT過半、兩岸領先封裝廠、東南亞封裝客戶；公司並規劃2026年打入3家晶圓廠 | G4: Bare wafer AOI、黃光/RDL AOI、Fan-out/Interposer AOI、IC載板AOI、AI server主板AOI、高階OM | H4: 半導體營收有望倍增；營收認列高峰落在2026年Q2後；由封裝跨入前段晶圓廠，產品涵蓋Wafer/FOPLP/Unit形式 | I4: 最像『半導體AOI平台股』，產品站點最完整，適合作為AOI主倉核心 | J4: https://www.ftnn.com.tw/news/512660
A5: 上市 | B5: 3563 | C5: 牧德 | D5: 核心AOI | E5: 先進封裝 / 半導體前段 / IC載板 / AI伺服器PCB AOI | F5: 日月光為公開驗證客戶與股東；另以全球PCB與高階載板客群為主 | G5: PCB AOI、Packaged IC Inspection & Metrology、Wafer AOI、FOWLP/FOPLP/矽光子檢查設備 | H5: AI伺服器/HPC/高階IC載板需求延續；半導體檢測設備持續推進客戶導入；2025 EPS 15.8元、2026前2月營收年增7.81% | I5: 品質最好、客戶最硬的AOI股之一，但不再是便宜貨，適合拉回承接 | J5: https://news.cnyes.com/news/id/6360450
A6: 上市 | B6: 3030 | C6: 德律 | D6: 核心AOI | E6: 先進封裝 / AI伺服器PCB AOI | F6: 網通/伺服器為最大應用領域，並切入晶圓廠與OSAT供應鏈（公開未逐一點名） | G6: SPI、AOI、AXI、ICT/BT/MDA、AI-powered 3D SEMI AOI，延伸至WLP/TSV/TGV/Glass RDL | H6: AI基建、AI伺服器與先進封裝帶動；2025年營收84.67億元創高，2026年前2月持續雙位數成長 | I6: 最穩健的AOI/檢測配置之一，適合保守型資金 | J6: https://www.ftnn.com.tw/news/512878
A7: 上市 | B7: 6658 | C7: 聯策 | D7: 交叉設備 | E7: AI伺服器PCB AOI / IC載板 / 半導體前段 | F7: 一線PCB/載板客戶、泰國載板客戶；重要股東含迅得、臻鼎-KY；半導體客戶未公開點名 | G7: AI機器視覺設備、檢測設備產線、PCB/載板自動化，並跨入晶圓檢測/量測設備 | H7: 新生廠量能開出、東南亞PCB外移擴產、半導體設備研發導入；2025 EPS 1.38元，訂單能見度到2026年Q2 | I7: 值得納入，但屬第二圈觀察，不應與由田/牧德/德律混為同級 | J7: https://uanalyze.com.tw/articles/7030747426
A8: 上市 | B8: 3167 | C8: 大量 | D8: 交叉設備 | E8: 先進封裝 / 半導體前段 / AI伺服器PCB AOI | F8: 台積電、日月光等指標客戶 | G8: Wafer邊緣量測、CMP Pad量測、Step-height量測、FOPLP翹曲量測、AOI、自動化；對應SoIC/InFO/CoWoS | H8: 先進封裝相關量測與AOI設備出貨擴大；2025年部分訂單遞延至2026年，能見度延續 | I8: 關鍵不是有沒有AOI，而是已吃到台積電/日月光先進封裝量測站點 | J8: https://ec.ltn.com.tw/article/paper/1668066

Sheet Category_矽光子CPO
A1: 矽光子/CPO 光學耦合與檢測 廠商列表
A3: 市場別 | B3: 代號 | C3: 公司 | D3: 主分類 | E3: 次分類 | F3: 確定客戶/客群 | G3: 產品站點 | H3: 2026成長催化 | I3: 最後結論 | J3: 來源
A4: 興櫃 | B4: 4573 | C4: 高明鐵 | D4: 交叉設備 | E4: 矽光子 / CPO 光學耦合與晶圓級測試 | F4: CPO光引擎、AI伺服器光模組與矽光晶圓測試/封裝客群；市場點名卡位台積電CPO鏈 | G4: 主動對準、晶圓級耦光測試、光引擎找光/對準/鎖光、CPO/矽光子封裝測試 | H4: 800G放量、1.6T少量生產與2026矽光子商轉；元月營收年增93.49%，受惠高速互連升級 | I4: 應納入名單，但要獨立歸類為矽光子/CPO光學耦合與量測設備，不宜硬塞進傳統AOI核心 | J4: https://money.udn.com/money/story/5735/8985170

Sheet 投資排序
A1: 公司 | B1: 代號 | C1: 市場別 | D1: 主分類 | E1: 技術護城河(25) | F1: 客戶驗證(20) | G1: 成長催化(20) | H1: 純度/站點(20) | I1: 風險報酬(15) | J1: 總分 | K1: 排名 | L1: 建議倉位 | M1: 主要觀察
A2: 由田 | B2: 3455 | C2: 上櫃 | D2: 核心AOI | E2: 23 | F2: 18 | G2: 19 | H2: 19 | I2: 12 | J2: =SUM(E2:I2) | K2: 1 | L2: =IF(J2>=90,"主倉 15-20%",IF(J2>=85,"核心倉 10-15%",IF(J2>=80,"衛星倉 5-10%",IF(J2>=75,"觀察倉 3-5%","觀察名單")))) | M2: AOI平台化最完整
A3: 牧德 | B3: 3563 | C3: 上市 | D3: 核心AOI | E3: 23 | F3: 19 | G3: 18 | H3: 18 | I3: 12 | J3: =SUM(E3:I3) | K3: 2 | L3: =IF(J3>=90,"主倉 15-20%",IF(J3>=85,"核心倉 10-15%",IF(J3>=80,"衛星倉 5-10%",IF(J3>=75,"觀察倉 3-5%","觀察名單")))) | M3: 品質最佳但估值較高
A4: 倍利科 | B4: 7822 | C4: 興櫃/即將上市 | D4: 核心AOI | E4: 24 | F4: 17 | G4: 19 | H4: 18 | I4: 11 | J4: =SUM(E4:I4) | K4: 3 | L4: =IF(J4>=90,"主倉 15-20%",IF(J4>=85,"核心倉 10-15%",IF(J4>=80,"衛星倉 5-10%",IF(J4>=75,"觀察倉 3-5%","觀察名單")))) | M4: AI原生AOI、高成長高波動
A5: 德律 | B5: 3030 | C5: 上市 | D5: 核心AOI | E5: 21 | F5: 18 | G5: 18 | H5: 16 | I5: 15 | J5: =SUM(E5:I5) | K5: 4 | L5: =IF(J5>=90,"主倉 15-20%",IF(J5>=85,"核心倉 10-15%",IF(J5>=80,"衛星倉 5-10%",IF(J5>=75,"觀察倉 3-5%","觀察名單")))) | M5: 最穩健的AOI/檢測配置
A6: 晶彩科 | B6: 3535 | C6: 上市 | D6: 核心AOI | E6: 21 | F6: 16 | G6: 19 | H6: 18 | I6: 13 | J6: =SUM(E6:I6) | K6: 5 | L6: =IF(J6>=90,"主倉 15-20%",IF(J6>=85,"核心倉 10-15%",IF(J6>=80,"衛星倉 5-10%",IF(J6>=75,"觀察倉 3-5%","觀察名單")))) | M6: FOPLP/TGV彈性高
A7: 竑騰 | B7: 7751 | C7: 上櫃 | D7: 核心AOI | E7: 20 | F7: 17 | G7: 18 | H7: 16 | I7: 15 | J7: =SUM(E7:I7) | K7: 6 | L7: =IF(J7>=90,"主倉 15-20%",IF(J7>=85,"核心倉 10-15%",IF(J7>=80,"衛星倉 5-10%",IF(J7>=75,"觀察倉 3-5%","觀察名單")))) | M7: AI散熱封裝黑馬
A8: 大量 | B8: 3167 | C8: 上市 | D8: 交叉設備 | E8: 18 | F8: 18 | G8: 17 | H8: 14 | I8: 15 | J8: =SUM(E8:I8) | K8: 7 | L8: =IF(J8>=90,"主倉 15-20%",IF(J8>=85,"核心倉 10-15%",IF(J8>=80,"衛星倉 5-10%",IF(J8>=75,"觀察倉 3-5%","觀察名單")))) | M8: 先進封裝量測實績強
A9: 高明鐵 | B9: 4573 | C9: 興櫃 | D9: 交叉設備 | E9: 19 | F9: 15 | G9: 18 | H9: 13 | I9: 16 | J9: =SUM(E9:I9) | K9: 8 | L9: =IF(J9>=90,"主倉 15-20%",IF(J9>=85,"核心倉 10-15%",IF(J9>=80,"衛星倉 5-10%",IF(J9>=75,"觀察倉 3-5%","觀察名單")))) | M9: 矽光子/CPO新主線
A10: 均豪 | B10: 5443 | C10: 上櫃 | D10: 交叉設備 | E10: 18 | F10: 15 | G10: 17 | H10: 13 | I10: 15 | J10: =SUM(E10:I10) | K10: 9 | L10: =IF(J10>=90,"主倉 15-20%",IF(J10>=85,"核心倉 10-15%",IF(J10>=80,"衛星倉 5-10%",IF(J10>=75,"觀察倉 3-5%","觀察名單")))) | M10: 設備整合股、半導體轉型佳
A11: 聯策 | B11: 6658 | C11: 上市 | D11: 交叉設備 | E11: 16 | F11: 13 | G11: 15 | H11: 13 | I11: 14 | J11: =SUM(E11:I11) | K11: 10 | L11: =IF(J11>=90,"主倉 15-20%",IF(J11>=85,"核心倉 10-15%",IF(J11>=80,"衛星倉 5-10%",IF(J11>=75,"觀察倉 3-5%","觀察名單")))) | M11: 轉骨中，半導體貢獻待放大
A12: 鏵友益 | B12: 6877 | C12: 上櫃 | D12: 核心AOI | E12: 16 | F12: 14 | G12: 14 | H12: 15 | I12: 12 | J12: =SUM(E12:I12) | K12: 11 | L12: =IF(J12>=90,"主倉 15-20%",IF(J12>=85,"核心倉 10-15%",IF(J12>=80,"衛星倉 5-10%",IF(J12>=75,"觀察倉 3-5%","觀察名單")))) | M12: 小而純，仍在轉骨
A13: 東捷 | B13: 8064 | C13: 上櫃 | D13: 交叉設備 | E13: 15 | F13: 12 | G13: 14 | H13: 12 | I13: 13 | J13: =SUM(E13:I13) | K13: 12 | L13: =IF(J13>=90,"主倉 15-20%",IF(J13>=85,"核心倉 10-15%",IF(J13>=80,"衛星倉 5-10%",IF(J13>=75,"觀察倉 3-5%","觀察名單")))) | M13: 次核心觀察

Sheet Memo_由田
A1: 由田（3455）法人備忘錄
A3: 市場別 | B3: 上櫃 | D3: 投資總分 | E3: ='投資排序'!J2
A4: 主分類 | B4: 核心AOI | D4: 建議倉位 | E4: ='投資排序'!L2
A5: 次分類 | B5: 半導體前段 / 先進封裝 / IC載板 / AI伺服器PCB AOI | D5: 主要觀察 | E5: ='投資排序'!M2
A6: 上游供應商 | B6: 工業相機、鏡頭、光源、精密平台、機器視覺與演算法模組供應鏈
A7: 確定客戶/客群 | B7: 前十大OSAT過半、兩岸領先封裝廠、東南亞封裝客戶；公司並規劃2026年打入3家晶圓廠 | D7: 使用說明
A8: 產品站點 | B8: Bare wafer AOI、黃光/RDL AOI、Fan-out/Interposer AOI、IC載板AOI、AI server主板AOI、高階OM | D8: 本備忘錄屬投資研究用途，買點/停損為波段技術紀律，不代表保證獲利。
A9: 2026成長催化 | B9: 半導體營收有望倍增；營收認列高峰落在2026年Q2後；由封裝跨入前段晶圓廠，產品涵蓋Wafer/FOPLP/Unit形式 | D9: 技術面實作重點：量縮回測、均線支撐、KD/MACD不惡化、跌破平台/季線撤退。
A10: 最大風險 | B10: 驗證與認列節奏不平滑、交期較長；若晶圓廠導入遞延，市場會先修正估值
A11: 買點邏輯 | B11: 不追長紅；等量縮回測10/20日線不破、MACD未翻空、KD回落後再上彎時分批承接
A12: 停損邏輯 | B12: 跌破前波平台且爆量失守20日線先砍半；若連60日線都失守，代表認列預期轉弱應退場
A13: 最後結論 | B13: 最像『半導體AOI平台股』，產品站點最完整，適合作為AOI主倉核心
A14: 來源1 | B14: https://www.ftnn.com.tw/news/512660
A15: 來源2 | B15: https://news.cnyes.com/news/id/5633834

Sheet Memo_牧德
A1: 牧德（3563）法人備忘錄
A3: 市場別 | B3: 上市 | D3: 投資總分 | E3: ='投資排序'!J3
A4: 主分類 | B4: 核心AOI | D4: 建議倉位 | E4: ='投資排序'!L3
A5: 次分類 | B5: 先進封裝 / 半導體前段 / IC載板 / AI伺服器PCB AOI | D5: 主要觀察 | E5: ='投資排序'!M3
A6: 上游供應商 | B6: 光學、控制、量測與演算法模組供應鏈
A7: 確定客戶/客群 | B7: 日月光為公開驗證客戶與股東；另以全球PCB與高階載板客群為主 | D7: 使用說明
A8: 產品站點 | B8: PCB AOI、Packaged IC Inspection & Metrology、Wafer AOI、FOWLP/FOPLP/矽光子檢查設備 | D8: 本備忘錄屬投資研究用途，買點/停損為波段技術紀律，不代表保證獲利。
A9: 2026成長催化 | B9: AI伺服器/HPC/高階IC載板需求延續；半導體檢測設備持續推進客戶導入；2025 EPS 15.8元、2026前2月營收年增7.81% | D9: 技術面實作重點：量縮回測、均線支撐、KD/MACD不惡化、跌破平台/季線撤退。
A10: 最大風險 | B10: 估值已高、好消息已部分反映；若Wafer/FOPLP驗證放量時程遞延，股價容易高檔震盪
A11: 買點邏輯 | B11: 只做強勢股拉回買；等5日線乖離收斂、量縮回測10日線或前高不破再接
A12: 停損邏輯 | B12: 爆量長黑跌破20日線先降部位；跌破前波平台且MACD柱狀體翻負擴大則不戀戰
A13: 最後結論 | B13: 品質最好、客戶最硬的AOI股之一，但不再是便宜貨，適合拉回承接
A14: 來源1 | B14: https://news.cnyes.com/news/id/6360450
A15: 來源2 | B15: https://www.cna.com.tw/news/aie/202506190204.aspx

Sheet Memo_晶彩科
A1: 晶彩科（3535）法人備忘錄
A3: 市場別 | B3: 上市 | D3: 投資總分 | E3: ='投資排序'!J6
A4: 主分類 | B4: 核心AOI | D4: 建議倉位 | E4: ='投資排序'!L6
A5: 次分類 | B5: 先進封裝 / 半導體前段 / IC載板 | D5: 主要觀察 | E5: ='投資排序'!M6
A6: 上游供應商 | B6: 光學檢測、量測平台、AI缺陷辨識與對位模組供應鏈
A7: 確定客戶/客群 | B7: 知名封測大廠採用；半導體設備已通過認證並取得訂單（公開未點名） | D7: 使用說明
A8: 產品站點 | B8: Wafer AI AOI、3D IC Die Location、FOPLP/FOWLP Die Location Metrology、TGV/玻璃基板檢量測 | D8: 本備忘錄屬投資研究用途，買點/停損為波段技術紀律，不代表保證獲利。
A9: 2026成長催化 | B9: FOPLP/TGV/玻璃基板與AI AOI需求升溫；2026年訂單看倍數成長，第四季以來營收明顯回升 | D9: 技術面實作重點：量縮回測、均線支撐、KD/MACD不惡化、跌破平台/季線撤退。
A10: 最大風險 | B10: 客製案與量產案比重高，財報波動大；若FOPLP/TGV量產時程不如預期，題材先回檔
A11: 買點邏輯 | B11: 不追連續漲停；等爆量後首次量縮整理，確認10日線與缺口有守再介入
A12: 停損邏輯 | B12: 失守平台且量能擴大時應快速停損，避免題材退潮
A13: 最後結論 | B13: 真正的價值在AOI+Metrology，若FOPLP/TGV成形，彈性很大
A14: 來源1 | B14: https://www.chinatimes.com/newspapers/20260122000409-260206
A15: 來源2 | B15: https://www.favite.com/en/

Sheet Memo_德律
A1: 德律（3030）法人備忘錄
A3: 市場別 | B3: 上市 | D3: 投資總分 | E3: ='投資排序'!J5
A4: 主分類 | B4: 核心AOI | D4: 建議倉位 | E4: ='投資排序'!L5
A5: 次分類 | B5: 先進封裝 / AI伺服器PCB AOI | D5: 主要觀察 | E5: ='投資排序'!M5
A6: 上游供應商 | B6: 感測、光學、X-ray、運控與測試模組供應鏈
A7: 確定客戶/客群 | B7: 網通/伺服器為最大應用領域，並切入晶圓廠與OSAT供應鏈（公開未逐一點名） | D7: 使用說明
A8: 產品站點 | B8: SPI、AOI、AXI、ICT/BT/MDA、AI-powered 3D SEMI AOI，延伸至WLP/TSV/TGV/Glass RDL | D8: 本備忘錄屬投資研究用途，買點/停損為波段技術紀律，不代表保證獲利。
A9: 2026成長催化 | B9: AI基建、AI伺服器與先進封裝帶動；2025年營收84.67億元創高，2026年前2月持續雙位數成長 | D9: 技術面實作重點：量縮回測、均線支撐、KD/MACD不惡化、跌破平台/季線撤退。
A10: 最大風險 | B10: 股價不便宜但彈性通常不如題材股；若伺服器CAPEX轉弱，評價易受壓抑
A11: 買點邏輯 | B11: 趨勢回檔承接；量縮回測10/20日線不破可分批
A12: 停損邏輯 | B12: 高檔爆量長黑、跌破20日線且5日線下彎時收縮部位
A13: 最後結論 | B13: 最穩健的AOI/檢測配置之一，適合保守型資金
A14: 來源1 | B14: https://www.ftnn.com.tw/news/512878
A15: 來源2 | B15: https://www.ftnn.com.tw/news/449172

Sheet Memo_聯策
A1: 聯策（6658）法人備忘錄
A3: 市場別 | B3: 上市 | D3: 投資總分 | E3: ='投資排序'!J11
A4: 主分類 | B4: 交叉設備 | D4: 建議倉位 | E4: ='投資排序'!L11
A5: 次分類 | B5: AI伺服器PCB AOI / IC載板 / 半導體前段 | D5: 主要觀察 | E5: ='投資排序'!M11
A6: 上游供應商 | B6: AI機器視覺、高階自動化、智慧製程整合供應鏈
A7: 確定客戶/客群 | B7: 一線PCB/載板客戶、泰國載板客戶；重要股東含迅得、臻鼎-KY；半導體客戶未公開點名 | D7: 使用說明
A8: 產品站點 | B8: AI機器視覺設備、檢測設備產線、PCB/載板自動化，並跨入晶圓檢測/量測設備 | D8: 本備忘錄屬投資研究用途，買點/停損為波段技術紀律，不代表保證獲利。
A9: 2026成長催化 | B9: 新生廠量能開出、東南亞PCB外移擴產、半導體設備研發導入；2025 EPS 1.38元，訂單能見度到2026年Q2 | D9: 技術面實作重點：量縮回測、均線支撐、KD/MACD不惡化、跌破平台/季線撤退。
A10: 最大風險 | B10: 半導體設備營收占比尚未顯性化；若只是PCB自動化成長，市場不會給純AOI估值
A11: 買點邏輯 | B11: 站穩20日線、量能溫和放大、回測不破再買，適合作補漲與轉骨觀察股
A12: 停損邏輯 | B12: 跌回整理平台下緣或放量跌破20日線就先退
A13: 最後結論 | B13: 值得納入，但屬第二圈觀察，不應與由田/牧德/德律混為同級
A14: 來源1 | B14: https://uanalyze.com.tw/articles/7030747426
A15: 來源2 | B15: https://udn.com/news/story/7253/8795635

Sheet Memo_鏵友益
A1: 鏵友益（6877）法人備忘錄
A3: 市場別 | B3: 上櫃 | D3: 投資總分 | E3: ='投資排序'!J12
A4: 主分類 | B4: 核心AOI | D4: 建議倉位 | E4: ='投資排序'!L12
A5: 次分類 | B5: 先進封裝 / 半導體前段 | D5: 主要觀察 | E5: ='投資排序'!M12
A6: 上游供應商 | B6: AOI模組、自動化零組件與OEM配套供應鏈
A7: 確定客戶/客群 | B7: 日月光供應鏈、半導體封測與晶圓客群；與牧德結盟（部分客戶公開報導曾提及聯電/日月光） | D7: 使用說明
A8: 產品站點 | B8: AOI檢測設備、智能自動化設備、半導體微觀/鉅觀視覺檢查、Wafer AOI | D8: 本備忘錄屬投資研究用途，買點/停損為波段技術紀律，不代表保證獲利。
A9: 2026成長催化 | B9: 轉型半導體視覺檢查業務，與牧德結盟可望擴大Wafer AOI與封裝自動化接單 | D9: 技術面實作重點：量縮回測、均線支撐、KD/MACD不惡化、跌破平台/季線撤退。
A10: 最大風險 | B10: 2025 EPS僅0.59元，轉型尚未完全反映；獲利波動大
A11: 買點邏輯 | B11: 只能用轉機股打法；等營收連續回升、量價同步、站穩季線再看
A12: 停損邏輯 | B12: 跌破季線且無量承接時先退出
A13: 最後結論 | B13: 小而純但仍在轉骨，不適合當主倉
A14: 來源1 | B14: https://www.chinatimes.com/newspapers/20250319000332-260206
A15: 來源2 | B15: https://gfemobile.cnyes.com/news/id/6342921

Sheet Memo_竑騰
A1: 竑騰（7751）法人備忘錄
A3: 市場別 | B3: 上櫃 | D3: 投資總分 | E3: ='投資排序'!J7
A4: 主分類 | B4: 核心AOI | D4: 建議倉位 | E4: ='投資排序'!L7
A5: 次分類 | B5: 先進封裝 AOI / AI散熱封裝 | D5: 主要觀察 | E5: ='投資排序'!M7
A6: 上游供應商 | B6: 精密機構、點膠/壓合、熱壓控制、AOI視覺與TIM製程模組
A7: 確定客戶/客群 | B7: 台積電、日月光、矽品、力成等前七大封測業者供應鏈 | D7: 使用說明
A8: 產品站點 | B8: 點膠植片壓合機、Metal TIM/散熱片貼合、自動光學檢測（AOI）設備 | D8: 本備忘錄屬投資研究用途，買點/停損為波段技術紀律，不代表保證獲利。
A9: 2026成長催化 | B9: AI/GPU/HPC高功耗帶動散熱封裝升級；2026年1月營收年增80.57%，市場看好接單延續 | D9: 技術面實作重點：量縮回測、均線支撐、KD/MACD不惡化、跌破平台/季線撤退。
A10: 最大風險 | B10: 高成長也高波動；客戶集中於封測龍頭，若CAPEX遞延彈性會反向放大
A11: 買點邏輯 | B11: 等第一次大漲後量縮整理、5日線重新上彎再介入，採分批策略
A12: 停損邏輯 | B12: 失守20日線且帶量先退；高檔爆量長黑吞噬前兩日視為主力換手失敗
A13: 最後結論 | B13: AI散熱/先進封裝黑馬，硬邏輯成立，但波動極大
A14: 來源1 | B14: https://money.udn.com/money/amp/story/5607/9341183
A15: 來源2 | B15: https://www.taisounds.com/news/content/76/204366

Sheet Memo_倍利科
A1: 倍利科（7822）法人備忘錄
A3: 市場別 | B3: 興櫃/即將上市 | D3: 投資總分 | E3: ='投資排序'!J4
A4: 主分類 | B4: 核心AOI | D4: 建議倉位 | E4: ='投資排序'!L4
A5: 次分類 | B5: 半導體前段 / 先進封裝 | D5: 主要觀察 | E5: ='投資排序'!M4
A6: 上游供應商 | B6: 光學、精密機械、電控、軟體與AI整合供應鏈
A7: 確定客戶/客群 | B7: 晶圓製造廠、先進封裝廠、記憶體廠；已導入逾10家半導體客戶、上線逾800台 | D7: 使用說明
A8: 產品站點 | B8: 高階Auto OM、高倍率量測（CD/OVL）、AI ADC影像數據分析、缺陷辨識系統 | D8: 本備忘錄屬投資研究用途，買點/停損為波段技術紀律，不代表保證獲利。
A9: 2026成長催化 | B9: 2025營收20.75億元年增187.82%；受惠先進製程/先進封裝擴產，2026預計3/30掛牌上市 | D9: 技術面實作重點：量縮回測、均線支撐、KD/MACD不惡化、跌破平台/季線撤退。
A10: 最大風險 | B10: 上市初期估值與流動性波動大；高成長基期下任何季節性放緩都會被放大
A11: 買點邏輯 | B11: 不要追上市蜜月；等第一波情緒高點過後、回測關鍵均線有守再接
A12: 停損邏輯 | B12: 跌破上市後第一個整理平台時嚴格停損
A13: 最後結論 | B13: 最像AI原生AOI，技術護城河在AI缺陷資料庫與演算法
A14: 來源1 | B14: https://udn.com/news/story/7254/9359635
A15: 來源2 | B15: https://www.mnews.tw/external/mirrordaily49130

Sheet Memo_均豪
A1: 均豪（5443）法人備忘錄
A3: 市場別 | B3: 上櫃 | D3: 投資總分 | E3: ='投資排序'!J10
A4: 主分類 | B4: 交叉設備 | D4: 建議倉位 | E4: ='投資排序'!L10
A5: 次分類 | B5: 先進封裝 / IC載板 | D5: 主要觀察 | E5: ='投資排序'!M10
A6: 上游供應商 | B6: 檢、量、磨、拋與製程整合設備供應鏈
A7: 確定客戶/客群 | B7: 封測大廠與再生晶圓客戶（公開未點名） | D7: 使用說明
A8: 產品站點 | B8: CMP結合AOI檢測、多段拋光、白光檢測量測Bump高度/間距、IC載板AOI相關設備 | D8: 本備忘錄屬投資研究用途，買點/停損為波段技術紀律，不代表保證獲利。
A9: 2026成長催化 | B9: AI晶片散熱與先進封裝升級；2026年半導體營收占比目標逾8成，再生晶圓與先進封測為雙主軸 | D9: 技術面實作重點：量縮回測、均線支撐、KD/MACD不惡化、跌破平台/季線撤退。
A10: 最大風險 | B10: 設備組合多元，市場難以給純AOI估值；若先進封裝CAPEX不如預期，題材張力會下降
A11: 買點邏輯 | B11: 偏波段股打法；站穩20日線、量能溫和放大可續抱
A12: 停損邏輯 | B12: 衝高後量價背離、跌回整理區時先減碼
A13: 最後結論 | B13: 不是最純，但往往比市場想像中更受惠於先進封測設備整合
A14: 來源1 | B14: https://udn.com/news/story/7254/9367100
A15: 來源2 | B15: https://udn.com/news/story/7253/9132993

Sheet Memo_大量
A1: 大量（3167）法人備忘錄
A3: 市場別 | B3: 上市 | D3: 投資總分 | E3: ='投資排序'!J8
A4: 主分類 | B4: 交叉設備 | D4: 建議倉位 | E4: ='投資排序'!L8
A5: 次分類 | B5: 先進封裝 / 半導體前段 / AI伺服器PCB AOI | D5: 主要觀察 | E5: ='投資排序'!M8
A6: 上游供應商 | B6: 量測模組、AOI光學、自動化與機構供應鏈
A7: 確定客戶/客群 | B7: 台積電、日月光等指標客戶 | D7: 使用說明
A8: 產品站點 | B8: Wafer邊緣量測、CMP Pad量測、Step-height量測、FOPLP翹曲量測、AOI、自動化；對應SoIC/InFO/CoWoS | D8: 本備忘錄屬投資研究用途，買點/停損為波段技術紀律，不代表保證獲利。
A9: 2026成長催化 | B9: 先進封裝相關量測與AOI設備出貨擴大；2025年部分訂單遞延至2026年，能見度延續 | D9: 技術面實作重點：量縮回測、均線支撐、KD/MACD不惡化、跌破平台/季線撤退。
A10: 最大風險 | B10: 股價曾快速飆漲，若單月營收或新單節奏不連續，修正會很快
A11: 買點邏輯 | B11: 只在強勢整理後再發動時介入，不追噴出
A12: 停損邏輯 | B12: 跌破月線且量增、KD/MACD同步走弱時停利/停損都要快
A13: 最後結論 | B13: 關鍵不是有沒有AOI，而是已吃到台積電/日月光先進封裝量測站點
A14: 來源1 | B14: https://ec.ltn.com.tw/article/paper/1668066
A15: 來源2 | B15: https://news.cnyes.com/news/print/6262663

Sheet Memo_東捷
A1: 東捷（8064）法人備忘錄
A3: 市場別 | B3: 上櫃 | D3: 投資總分 | E3: ='投資排序'!J13
A4: 主分類 | B4: 交叉設備 | D4: 建議倉位 | E4: ='投資排序'!L13
A5: 次分類 | B5: 先進封裝 / 玻璃載板 / FOPLP | D5: 主要觀察 | E5: ='投資排序'!M13
A6: 上游供應商 | B6: 雷射、光學量測與先進封裝製程設備模組供應鏈
A7: 確定客戶/客群 | B7: 先進封裝與面板/FOPLP客戶（公開未逐一點名） | D7: 使用說明
A8: 產品站點 | B8: RDL雷射線路修補設備（搭載自動光學量測）、玻璃載板雷射切割、AOI設備、電漿清潔 | D8: 本備忘錄屬投資研究用途，買點/停損為波段技術紀律，不代表保證獲利。
A9: 2026成長催化 | B9: 先進封裝設備訂單增長，2026年半導體設備比重有望拉升到30%以上；受惠FOPLP與玻璃基板 | D9: 技術面實作重點：量縮回測、均線支撐、KD/MACD不惡化、跌破平台/季線撤退。
A10: 最大風險 | B10: 不是純AOI且營收認列偏集中；當主線轉向更純的AOI/封測設備股時容易被邊緣化
A11: 買點邏輯 | B11: 題材輪動時短打；站穩季線再看
A12: 停損邏輯 | B12: 跌破季線就撤，不當長抱核心
A13: 最後結論 | B13: 能看，但排序應放後面，較適合次核心觀察
A14: 來源1 | B14: https://www.chinatimes.com/newspapers/20251127000364-260206
A15: 來源2 | B15: https://udn.com/news/story/7240/8581331

Sheet Memo_高明鐵
A1: 高明鐵（4573）法人備忘錄
A3: 市場別 | B3: 興櫃 | D3: 投資總分 | E3: ='投資排序'!J9
A4: 主分類 | B4: 交叉設備 | D4: 建議倉位 | E4: ='投資排序'!L9
A5: 次分類 | B5: 矽光子 / CPO 光學耦合與晶圓級測試 | D5: 主要觀察 | E5: ='投資排序'!M9
A6: 上游供應商 | B6: 六軸平台、AI影像伺服、6D雷射量測與高精度運動控制供應鏈
A7: 確定客戶/客群 | B7: CPO光引擎、AI伺服器光模組與矽光晶圓測試/封裝客群；市場點名卡位台積電CPO鏈 | D7: 使用說明
A8: 產品站點 | B8: 主動對準、晶圓級耦光測試、光引擎找光/對準/鎖光、CPO/矽光子封裝測試 | D8: 本備忘錄屬投資研究用途，買點/停損為波段技術紀律，不代表保證獲利。
A9: 2026成長催化 | B9: 800G放量、1.6T少量生產與2026矽光子商轉；元月營收年增93.49%，受惠高速互連升級 | D9: 技術面實作重點：量縮回測、均線支撐、KD/MACD不惡化、跌破平台/季線撤退。
A10: 最大風險 | B10: 非傳統AOI主線；若CPO量產時程遞延，題材修正會很快，營收波動也較大
A11: 買點邏輯 | B11: 放量突破平台後，等第一次量縮回測10/20日線不破再進
A12: 停損邏輯 | B12: 跌回突破平台下方，或爆量長黑失守20日線先退
A13: 最後結論 | B13: 應納入名單，但要獨立歸類為矽光子/CPO光學耦合與量測設備，不宜硬塞進傳統AOI核心
A14: 來源1 | B14: https://money.udn.com/money/story/5735/8985170
A15: 來源2 | B15: https://www.ftnn.com.tw/news/519647

Sheet 方法與註記
A1: 篩選邏輯與評分註記
A3: 名單定義 | B3: 納入台灣公開市場（上市/上櫃/興櫃）中，已明確切入 AI、半導體前段、先進封裝、IC載板、AI伺服器PCB AOI，或矽光子/CPO 光學耦合與檢測設備的公司。
A4: 核心AOI | B4: 以 AOI/光學檢測/檢量測為公司核心定位。
A5: 交叉設備 | B5: 非純 AOI，但已有 AOI、光學量測、耦光測試、白光檢測或先進封裝量測設備切入相關供應鏈。
A6: 評分方式 | B6: 總分 = 技術護城河(25) + 客戶驗證(20) + 成長催化(20) + 純度/站點(20) + 風險報酬(15)。
A7: 倉位建議 | B7: 90分以上主倉；85-89核心倉；80-84衛星倉；75-79觀察倉；75分以下列觀察名單。
A8: 來源原則 | B8: 來源欄位使用 plain text URL；以公開媒體報導與公司/產品頁可交叉驗證資訊為主。
